konsensus/constants.py
konsensus/entities/__init__.py
konsensus/entities/data_types.py
konsensus/entities/messages_types.py
konsensus/infra/logger.py
konsensus/models/member.py
konsensus/models/node.py
konsensus/models/roles/__init__.py
konsensus/models/roles/acceptor.py
konsensus/models/roles/bootstrap.py
konsensus/models/roles/commander.py
konsensus/models/roles/leader.py
konsensus/models/roles/replica.py
konsensus/models/roles/requester.py
konsensus/models/roles/scout.py
konsensus/models/roles/seed.py
konsensus/models/timer.py
konsensus/network.py
konsensus-0.1.4.dist-info/LICENSE
konsensus-0.1.4.dist-info/METADATA
konsensus-0.1.4.dist-info/WHEEL
konsensus-0.1.4.dist-info/RECORD
