Metadata-Version: 2.1
Name: konsensus
Version: 0.1.4
Summary: Simple clustering by consensus library
License: MIT
Keywords: konsensus,paxos,consensus
Author: BrianLusina
Author-email: 12752833+BrianLusina@users.noreply.github.com
Requires-Python: >=3.10,<4.0
Classifier: License :: OSI Approved :: MIT License
Classifier: Programming Language :: Python
Classifier: Programming Language :: Python :: 3
Classifier: Programming Language :: Python :: 3.10
Classifier: Programming Language :: Python :: 3.11
Classifier: Programming Language :: Python :: 3
